wdltest/__init__.py
wdltest/conf.py
wdltest/cromwell.cfg
wdltest/cromwell_handler.py
wdltest/system_utils.py
wdltest/test_configuration.py
wdltest/test_runner.py
wdltest/wdltest.cfg
wdltest/wdltest.py
wdltest-1.15.0.data/scripts/wdltest
wdltest-1.15.0.dist-info/LICENSE
wdltest-1.15.0.dist-info/METADATA
wdltest-1.15.0.dist-info/WHEEL
wdltest-1.15.0.dist-info/top_level.txt
wdltest-1.15.0.dist-info/RECORD
