Metadata-Version: 2.1
Name: wdltest
Version: 1.15.0
Summary: Package for testing wdl workflows
Home-page: https://github.com/marpiech/wdltest
Author: Marcin Piechota
Author-email: piechota.marcin@gmail.com
License: UNKNOWN
Platform: UNKNOWN
Classifier: Programming Language :: Python :: 3
Classifier: License :: OSI Approved :: MIT License
Classifier: Operating System :: OS Independent
Requires-Python: >=3.6
Requires-Dist: regex
Requires-Dist: threaded
